gdc/__init__.py
gdc/__main__.py
gdc/gdc.py
github_download_count-0.0.1.dist-info/DESCRIPTION.rst
github_download_count-0.0.1.dist-info/METADATA
github_download_count-0.0.1.dist-info/RECORD
github_download_count-0.0.1.dist-info/WHEEL
github_download_count-0.0.1.dist-info/entry_points.txt
github_download_count-0.0.1.dist-info/metadata.json
github_download_count-0.0.1.dist-info/top_level.txt
