Metadata-Version: 2.0
Name: github-download-count
Version: 0.0.1
Summary: Display download counts of GitHub releases
Home-page: https://github.com/brbsix/github-download-count
Author: Brian Beffa
Author-email: brbsix@gmail.com
License: GPLv3
Keywords: GitHub,API,release,download,count
Platform: UNKNOWN
Classifier: Development Status :: 4 - Beta
Classifier: Environment :: Console
Classifier: Intended Audience :: Developers
Classifier: Intended Audience :: End Users/Desktop
Classifier: License :: OSI Approved :: GNU General Public License v3 (GPLv3)
Classifier: Natural Language :: English
Classifier: Operating System :: POSIX
Classifier: Operating System :: POSIX :: Linux
Classifier: Programming Language :: Python :: 2
Classifier: Programming Language :: Python :: 2.6
Classifier: Programming Language :: Python :: 2.7
Classifier: Programming Language :: Python :: 3
Classifier: Programming Language :: Python :: 3.0
Classifier: Programming Language :: Python :: 3.1
Classifier: Programming Language :: Python :: 3.2
Classifier: Programming Language :: Python :: 3.3
Classifier: Programming Language :: Python :: 3.4
Classifier: Programming Language :: Python :: 3 :: Only
Classifier: Topic :: Utilities
Requires-Dist: requests
Provides-Extra: testing
Requires-Dist: pytest-cov; extra == 'testing'
Requires-Dist: pytest-pylint; extra == 'testing'
Requires-Dist: requests-mock; extra == 'testing'
